{
  "Transactions": [
    {
      "Date": "2023-01-25",
      "Description": "Deposit from Side Job",
      "Amount": 500.0,
      "Direction": "Paid In",
      "Balance": 2579.5
    },
    {
      "Date": "2023-01-30",
      "Description": "Monthly Subscription Service",
      "Amount": 15.99,
      "Direction": "Paid Out",
      "Balance": 2563.51
    },
    {
      "Date": "2023-01-05",
      "Description": "Deposit from Employer",
      "Amount": 1500.0,
      "Direction": "Paid In",
      "Balance": 2500.0
    },
    {
      "Date": "2023-01-10",
      "Description": "Grocery Store Purchase",
      "Amount": 120.5,
      "Direction": "Paid Out",
      "Balance": 2379.5
    },
    {
      "Date": "2023-01-15",
      "Description": "Utilities Payment",
      "Amount": 200.0,
      "Direction": "Paid Out",
      "Balance": 2179.5
    },
    {
      "Date": "2023-01-20",
      "Description": "ATM Withdrawal",
      "Amount": 100.0,
      "Direction": "Paid Out",
      "Balance": 2079.5
    },
    {
      "Date": "2023-01-01",
      "Description": "Opening Balance",
      "Amount": 0.0,
      "Direction": "Paid In",
      "Balance": 1000.0
    }
  ]
}