{"Transactions":[{"Date":"2023-10-01","Description":"Deposit - Employer","Amount":1200,"Direction":"Paid In","Balance":1200},{"Date":"2023-10-05","Description":"ATM Withdrawal","Amount":300,"Direction":"Paid Out","Balance":900},{"Date":"2023-10-10","Description":"Grocery Store Purchase","Amount":150,"Direction":"Paid Out","Balance":750},{"Date":"2023-10-15","Description":"Online Subscription Service","Amount":15,"Direction":"Paid Out","Balance":735},{"Date":"2023-10-20","Description":"Utility Bill Payment","Amount":100,"Direction":"Paid Out","Balance":635},{"Date":"2023-10-25","Description":"Transfer from Savings","Amount":200,"Direction":"Paid In","Balance":835},{"Date":"2023-10-30","Description":"Restaurant Bill","Amount":75,"Direction":"Paid Out","Balance":760}]}